scripts_main_service/__init__.py
scripts_main_service/plugin.py
scripts_main_service/version_util.py
scripts_main_service-0.0.2.dist-info/METADATA
scripts_main_service-0.0.2.dist-info/WHEEL
scripts_main_service-0.0.2.dist-info/RECORD
