Metadata-Version: 2.3
Name: scripts_main_service
Version: 0.0.2
Summary: 
Author: jybaby1027
Author-email: 18523852976@126.com
Requires-Python: >=3.11, <4.0
Classifier: Programming Language :: Python :: 3
Classifier: Programming Language :: Python :: 3.11
Classifier: Programming Language :: Python :: 3.12
Classifier: Programming Language :: Python :: 3.13
Provides-Extra: jupyter
Requires-Dist: facebook_plugin_banyan (>=0.0.1)
Requires-Dist: jupyter (>=1.1.0,<2.0.0) ; extra == "jupyter"
Requires-Dist: pytest (>=8.3.5,<9.0.0)
Requires-Dist: xcmap (>=0.0.1)
